msbase/ZMS_Starter.py
msbase/__init__.py
msbase/ms_base.py
msbase/ms_master.py
msbase/ms_server.py
msbase/ms_variables.py
msbase/ms_worker.py
msbasesvc-2.4.dist-info/METADATA
msbasesvc-2.4.dist-info/WHEEL
msbasesvc-2.4.dist-info/top_level.txt
msbasesvc-2.4.dist-info/RECORD
