Metadata-Version: 2.1
Name: msbasesvc
Version: 2.4
Summary: MS PY Base
Home-page: UNKNOWN
License: BSD
Platform: UNKNOWN
Requires-Dist: setuptools
Requires-Dist: loguru==0.7.2
Requires-Dist: nacos-sdk-python==0.1.14
Requires-Dist: snowflake-id==1.0.1
Requires-Dist: pytz==2024.1
Requires-Dist: PyYAML==6.0.1
Requires-Dist: grpc-interceptor==0.15.4
Requires-Dist: grpcio-health-checking==1.62.1
Requires-Dist: grpcio-reflection==1.62.1
Requires-Dist: grpcio-tools==1.62.1
Requires-Dist: h2==4.1.0
Requires-Dist: httpx==0.28.1
